{"0":{"0":null,"1":null,"2":null,"3":null,"4":null,"5":null,"6":null,"7":null,"8":null,"9":null,"10":null,"11":null,"12":null,"13":null,"14":null,"15":null,"16":null,"17":null,"18":null,"19":null,"20":null,"21":null,"22":null,"23":null,"24":null,"25":null},"1":{"0":null,"1":null,"2":"Wer ist dabei?","3":null,"4":"Kristian","5":"Reimund","6":"Karlheinz","7":"Jochen","8":"Bernd","9":null,"10":null,"11":null,"12":null,"13":null,"14":null,"15":null,"16":null,"17":"Ergebnisse: Welche Begriffe \/ Befehle haben wir bisher kennen gelernt?","18":"os.path","19":"List Comprehension","20":"os.env","21":"module","22":"listen vs array","23":"klassen (noch nicht klar)","24":null,"25":"multiprocessing"},"2":{"0":null,"1":null,"2":null,"3":null,"4":null,"5":null,"6":null,"7":null,"8":null,"9":null,"10":null,"11":null,"12":null,"13":null,"14":null,"15":null,"16":null,"17":null,"18":null,"19":null,"20":null,"21":null,"22":null,"23":null,"24":null,"25":null},"3":{"0":null,"1":null,"2":"W\u00fcnsche der Teilnehmer","3":null,"4":"Link zu 20 Standardfunktionen","5":"Strings suchen\/teilen\/ersetzen","6":"Link zu Hilfeseiten","7":null,"8":null,"9":null,"10":null,"11":null,"12":null,"13":null,"14":null,"15":null,"16":null,"17":null,"18":"os.system","19":"Variablen Deklaration","20":"Lesen und Beschreiben von Dateien","21":"unterschiedliche imports","22":"Funktionen definieren","23":"Schleifen","24":"Umgebungsvariable","25":null},"4":{"0":null,"1":null,"2":null,"3":null,"4":null,"5":null,"6":null,"7":null,"8":null,"9":null,"10":null,"11":null,"12":null,"13":null,"14":null,"15":null,"16":null,"17":null,"18":null,"19":null,"20":null,"21":null,"22":null,"23":null,"24":null,"25":null},"5":{"0":null,"1":null,"2":"Agenda","3":null,"4":"Donnerstag","5":"Python Automatisierung \u00dcberblick","6":"Dateiverwaltung automatisieren","7":"APIs automatisieren","8":null,"9":"Freitag","10":"Web-Browsing automatisieren","11":"Web-Scraping automatisieren","12":"GUI-Programme automatisieren","13":null,"14":"12:30-13:30 Mittag","15":null,"16":null,"17":null,"18":"Typannotation bei gro\u00dfen Programmen","19":"if und loops","20":null,"21":"Einr\u00fcckung","22":null,"23":null,"24":"open()","25":null},"6":{"0":null,"1":null,"2":null,"3":null,"4":null,"5":null,"6":null,"7":null,"8":null,"9":null,"10":null,"11":null,"12":null,"13":null,"14":null,"15":null,"16":null,"17":null,"18":null,"19":null,"20":null,"21":null,"22":null,"23":null,"24":null,"25":null},"7":{"0":null,"1":null,"2":"Fragen","3":null,"4":null,"5":"Reimund: os.system(f\"ls -la) auf remote systemen","6":"wie geht SSH \/ SCP aus Python","7":"Zugriff auf Ausgabe von Programmen","8":null,"9":"Dateien nach \u00c4nderungsdatum sortieren","10":null,"11":null,"12":1,"13":2,"14":3,"15":4,"16":null,"17":null,"18":null,"19":null,"20":null,"21":null,"22":null,"23":null,"24":null,"25":null}}